{"schema":{"version":{"fullVersion":"2.4.1","major":"2","minor":"4","patch":"1"},"meta":{"flags":["experimentalData"]},"collections":[{"name":"pages","label":"Pages","path":"content/pages","format":"md","ui":{},"fields":[{"name":"title","label":"Title","type":"string","required":true,"namespace":["pages","title"],"searchable":true,"uid":false},{"name":"hero","label":"Hero Section","type":"object","fields":[{"name":"tagline","label":"Tagline","type":"string","namespace":["pages","hero","tagline"],"searchable":true,"uid":false},{"name":"heading","label":"Heading","type":"string","namespace":["pages","hero","heading"],"searchable":true,"uid":false},{"name":"description","label":"Description","type":"string","ui":{"component":"textarea"},"namespace":["pages","hero","description"],"searchable":true,"uid":false},{"name":"ctaPrimary","label":"Primary CTA","type":"object","fields":[{"name":"text","label":"Text","type":"string","namespace":["pages","hero","ctaPrimary","text"],"searchable":true,"uid":false},{"name":"url","label":"URL","type":"string","namespace":["pages","hero","ctaPrimary","url"],"searchable":true,"uid":false}],"namespace":["pages","hero","ctaPrimary"],"searchable":true,"uid":false},{"name":"ctaSecondary","label":"Secondary CTA","type":"object","fields":[{"name":"text","label":"Text","type":"string","namespace":["pages","hero","ctaSecondary","text"],"searchable":true,"uid":false},{"name":"url","label":"URL","type":"string","namespace":["pages","hero","ctaSecondary","url"],"searchable":true,"uid":false}],"namespace":["pages","hero","ctaSecondary"],"searchable":true,"uid":false}],"namespace":["pages","hero"],"searchable":true,"uid":false},{"name":"services","label":"Services Section","type":"object","fields":[{"name":"heading","label":"Heading","type":"string","namespace":["pages","services","heading"],"searchable":true,"uid":false},{"name":"items","label":"Service Items","type":"object","list":true,"fields":[{"name":"title","label":"Title","type":"string","required":true,"namespace":["pages","services","items","title"],"searchable":true,"uid":false},{"name":"image","label":"Image","type":"image","namespace":["pages","services","items","image"],"searchable":false,"uid":false},{"name":"alt","label":"Alt Text","type":"string","namespace":["pages","services","items","alt"],"searchable":true,"uid":false},{"name":"description","label":"Description","type":"string","ui":{"component":"textarea"},"namespace":["pages","services","items","description"],"searchable":true,"uid":false}],"namespace":["pages","services","items"],"searchable":true,"uid":false}],"namespace":["pages","services"],"searchable":true,"uid":false},{"name":"lifts","label":"Lifts Section","type":"object","fields":[{"name":"badge","label":"Badge","type":"string","namespace":["pages","lifts","badge"],"searchable":true,"uid":false},{"name":"heading","label":"Heading","type":"string","namespace":["pages","lifts","heading"],"searchable":true,"uid":false},{"name":"description","label":"Description","type":"string","ui":{"component":"textarea"},"namespace":["pages","lifts","description"],"searchable":true,"uid":false}],"namespace":["pages","lifts"],"searchable":true,"uid":false},{"name":"aboutUs","label":"About Us Section","type":"object","fields":[{"name":"heading","label":"Heading","type":"string","namespace":["pages","aboutUs","heading"],"searchable":true,"uid":false},{"name":"description","label":"Description","type":"string","ui":{"component":"textarea"},"namespace":["pages","aboutUs","description"],"searchable":true,"uid":false},{"name":"descriptionSecondary","label":"Secondary Description","type":"string","ui":{"component":"textarea"},"namespace":["pages","aboutUs","descriptionSecondary"],"searchable":true,"uid":false},{"name":"stats","label":"Statistics","type":"object","list":true,"fields":[{"name":"value","label":"Value","type":"number","required":true,"namespace":["pages","aboutUs","stats","value"],"searchable":true,"uid":false},{"name":"label","label":"Label","type":"string","required":true,"namespace":["pages","aboutUs","stats","label"],"searchable":true,"uid":false}],"namespace":["pages","aboutUs","stats"],"searchable":true,"uid":false},{"name":"benefits","label":"Benefits","type":"object","list":true,"fields":[{"name":"text","label":"Benefit Text","type":"string","required":true,"namespace":["pages","aboutUs","benefits","text"],"searchable":true,"uid":false}],"namespace":["pages","aboutUs","benefits"],"searchable":true,"uid":false}],"namespace":["pages","aboutUs"],"searchable":true,"uid":false},{"name":"suppliers","label":"Suppliers Section","type":"object","fields":[{"name":"heading","label":"Heading","type":"string","namespace":["pages","suppliers","heading"],"searchable":true,"uid":false},{"name":"description","label":"Description","type":"string","ui":{"component":"textarea"},"namespace":["pages","suppliers","description"],"searchable":true,"uid":false},{"name":"logos","label":"Supplier Logos","type":"object","list":true,"fields":[{"name":"name","label":"Name","type":"string","namespace":["pages","suppliers","logos","name"],"searchable":true,"uid":false},{"name":"image","label":"Image","type":"image","namespace":["pages","suppliers","logos","image"],"searchable":false,"uid":false},{"name":"alt","label":"Alt Text","type":"string","namespace":["pages","suppliers","logos","alt"],"searchable":true,"uid":false}],"namespace":["pages","suppliers","logos"],"searchable":true,"uid":false}],"namespace":["pages","suppliers"],"searchable":true,"uid":false},{"name":"contact","label":"Contact Section","type":"object","fields":[{"name":"heading","label":"Heading","type":"string","namespace":["pages","contact","heading"],"searchable":true,"uid":false},{"name":"description","label":"Description","type":"string","ui":{"component":"textarea"},"namespace":["pages","contact","description"],"searchable":true,"uid":false},{"name":"phone","label":"Phone","type":"string","namespace":["pages","contact","phone"],"searchable":true,"uid":false},{"name":"email","label":"Email","type":"string","namespace":["pages","contact","email"],"searchable":true,"uid":false}],"namespace":["pages","contact"],"searchable":true,"uid":false},{"name":"faq","label":"FAQ Section","type":"object","fields":[{"name":"heading","label":"Heading","type":"string","namespace":["pages","faq","heading"],"searchable":true,"uid":false},{"name":"items","label":"FAQ Items","type":"object","list":true,"fields":[{"name":"question","label":"Question","type":"string","required":true,"namespace":["pages","faq","items","question"],"searchable":true,"uid":false},{"name":"answer","label":"Answer","type":"string","ui":{"component":"textarea"},"required":true,"namespace":["pages","faq","items","answer"],"searchable":true,"uid":false},{"name":"icon","label":"Icon","type":"string","options":["clock","wrench","cart","calendar","shield","payment","bag","support"],"namespace":["pages","faq","items","icon"],"searchable":true,"uid":false}],"namespace":["pages","faq","items"],"searchable":true,"uid":false}],"namespace":["pages","faq"],"searchable":true,"uid":false},{"name":"metaTitle","label":"Meta Title","type":"string","namespace":["pages","metaTitle"],"searchable":true,"uid":false},{"name":"metaDescription","label":"Meta Description","type":"string","ui":{"component":"textarea"},"namespace":["pages","metaDescription"],"searchable":true,"uid":false},{"name":"lastUpdate","label":"Last Update","type":"string","namespace":["pages","lastUpdate"],"searchable":true,"uid":false},{"name":"heading","label":"Page Heading","type":"string","namespace":["pages","heading"],"searchable":true,"uid":false},{"name":"tableOfContents","label":"Table of Contents","type":"object","list":true,"fields":[{"name":"label","label":"Label","type":"string","namespace":["pages","tableOfContents","label"],"searchable":true,"uid":false},{"name":"href","label":"Href","type":"string","namespace":["pages","tableOfContents","href"],"searchable":true,"uid":false}],"namespace":["pages","tableOfContents"],"searchable":true,"uid":false},{"name":"policySections","label":"Policy Sections","type":"object","list":true,"fields":[{"name":"id","label":"Section ID","type":"string","required":true,"namespace":["pages","policySections","id"],"searchable":true,"uid":false},{"name":"n","label":"Number","type":"number","required":true,"namespace":["pages","policySections","n"],"searchable":true,"uid":false},{"name":"title","label":"Title","type":"string","required":true,"namespace":["pages","policySections","title"],"searchable":true,"uid":false},{"name":"content","label":"Content","type":"rich-text","required":true,"namespace":["pages","policySections","content"],"searchable":true,"parser":{"type":"markdown"},"uid":false}],"namespace":["pages","policySections"],"searchable":true,"uid":false}],"namespace":["pages"]}],"config":{"media":{"tina":{"publicFolder":"public","mediaRoot":""}}}},"lookup":{"DocumentConnection":{"type":"DocumentConnection","resolveType":"multiCollectionDocumentList","collections":["pages"]},"Node":{"type":"Node","resolveType":"nodeDocument"},"DocumentNode":{"type":"DocumentNode","resolveType":"multiCollectionDocument","createDocument":"create","updateDocument":"update"},"Pages":{"type":"Pages","resolveType":"collectionDocument","collection":"pages","createPages":"create","updatePages":"update"},"PagesConnection":{"type":"PagesConnection","resolveType":"collectionDocumentList","collection":"pages"}},"graphql":{"kind":"Document","definitions":[{"kind":"ScalarTypeDefinition","name":{"kind":"Name","value":"Reference"},"description":{"kind":"StringValue","value":"References another document, used as a foreign key"},"directives":[]},{"kind":"ScalarTypeDefinition","name":{"kind":"Name","value":"JSON"},"description":{"kind":"StringValue","value":""},"directives":[]},{"kind":"ObjectTypeDefinition","interfaces":[],"directives":[],"name":{"kind":"Name","value":"SystemInfo"},"fields":[{"kind":"FieldDefinition","name":{"kind":"Name","value":"filename"},"arguments":[],"type":{"kind":"NonNullType","type":{"kind":"NamedType","name":{"kind":"Name","value":"String"}}}},{"kind":"FieldDefinition","name":{"kind":"Name","value":"title"},"arguments":[],"type":{"kind":"NamedType","name":{"kind":"Name","value":"String"}}},{"kind":"FieldDefinition","name":{"kind":"Name","value":"basename"},"arguments":[],"type":{"kind":"NonNullType","type":{"kind":"NamedType","name":{"kind":"Name","value":"String"}}}},{"kind":"FieldDefinition","name":{"kind":"Name","value":"hasReferences"},"arguments":[],"type":{"kind":"NamedType","name":{"kind":"Name","value":"Boolean"}}},{"kind":"FieldDefinition","name":{"kind":"Name","value":"breadcrumbs"},"arguments":[{"kind":"InputValueDefinition","name":{"kind":"Name","value":"excludeExtension"},"type":{"kind":"NamedType","name":{"kind":"Name","value":"Boolean"}}}],"type":{"kind":"NonNullType","type":{"kind":"ListType","type":{"kind":"NonNullType","type":{"kind":"NamedType","name":{"kind":"Name","value":"String"}}}}}},{"kind":"FieldDefinition","name":{"kind":"Name","value":"path"},"arguments":[],"type":{"kind":"NonNullType","type":{"kind":"NamedType","name":{"kind":"Name","value":"String"}}}},{"kind":"FieldDefinition","name":{"kind":"Name","value":"relativePath"},"arguments":[],"type":{"kind":"NonNullType","type":{"kind":"NamedType","name":{"kind":"Name","value":"String"}}}},{"kind":"FieldDefinition","name":{"kind":"Name","value":"extension"},"arguments":[],"type":{"kind":"NonNullType","type":{"kind":"NamedType","name":{"kind":"Name","value":"String"}}}},{"kind":"FieldDefinition","name":{"kind":"Name","value":"template"},"arguments":[],"type":{"kind":"NonNullType","type":{"kind":"NamedType","name":{"kind":"Name","value":"String"}}}},{"kind":"FieldDefinition","name":{"kind":"Name","value":"collection"},"arguments":[],"type":{"kind":"NonNullType","type":{"kind":"NamedType","name":{"kind":"Name","value":"Collection"}}}}]},{"kind":"ObjectTypeDefinition","interfaces":[],"directives":[],"name":{"kind":"Name","value":"Folder"},"fields":[{"kind":"FieldDefinition","name":{"kind":"Name","value":"name"},"arguments":[],"type":{"kind":"NonNullType","type":{"kind":"NamedType","name":{"kind":"Name","value":"String"}}}},{"kind":"FieldDefinition","name":{"kind":"Name","value":"path"},"arguments":[],"type":{"kind":"NonNullType","type":{"kind":"NamedType","name":{"kind":"Name","value":"String"}}}}]},{"kind":"ObjectTypeDefinition","interfaces":[],"directives":[],"name":{"kind":"Name","value":"PageInfo"},"fields":[{"kind":"FieldDefinition","name":{"kind":"Name","value":"hasPreviousPage"},"arguments":[],"type":{"kind":"NonNullType","type":{"kind":"NamedType","name":{"kind":"Name","value":"Boolean"}}}},{"kind":"FieldDefinition","name":{"kind":"Name","value":"hasNextPage"},"arguments":[],"type":{"kind":"NonNullType","type":{"kind":"NamedType","name":{"kind":"Name","value":"Boolean"}}}},{"kind":"FieldDefinition","name":{"kind":"Name","value":"startCursor"},"arguments":[],"type":{"kind":"NonNullType","type":{"kind":"NamedType","name":{"kind":"Name","value":"String"}}}},{"kind":"FieldDefinition","name":{"kind":"Name","value":"endCursor"},"arguments":[],"type":{"kind":"NonNullType","type":{"kind":"NamedType","name":{"kind":"Name","value":"String"}}}}]},{"kind":"InterfaceTypeDefinition","description":{"kind":"StringValue","value":""},"name":{"kind":"Name","value":"Node"},"interfaces":[],"directives":[],"fields":[{"kind":"FieldDefinition","name":{"kind":"Name","value":"id"},"arguments":[],"type":{"kind":"NonNullType","type":{"kind":"NamedType","name":{"kind":"Name","value":"ID"}}}}]},{"kind":"InterfaceTypeDefinition","description":{"kind":"StringValue","value":""},"name":{"kind":"Name","value":"Document"},"interfaces":[],"directives":[],"fields":[{"kind":"FieldDefinition","name":{"kind":"Name","value":"id"},"arguments":[],"type":{"kind":"NonNullType","type":{"kind":"NamedType","name":{"kind":"Name","value":"ID"}}}},{"kind":"FieldDefinition","name":{"kind":"Name","value":"_sys"},"arguments":[],"type":{"kind":"NamedType","name":{"kind":"Name","value":"SystemInfo"}}},{"kind":"FieldDefinition","name":{"kind":"Name","value":"_values"},"arguments":[],"type":{"kind":"NonNullType","type":{"kind":"NamedType","name":{"kind":"Name","value":"JSON"}}}}]},{"kind":"InterfaceTypeDefinition","description":{"kind":"StringValue","value":"A relay-compliant pagination connection"},"name":{"kind":"Name","value":"Connection"},"interfaces":[],"directives":[],"fields":[{"kind":"FieldDefinition","name":{"kind":"Name","value":"totalCount"},"arguments":[],"type":{"kind":"NonNullType","type":{"kind":"NamedType","name":{"kind":"Name","value":"Float"}}}},{"kind":"FieldDefinition","name":{"kind":"Name","value":"pageInfo"},"arguments":[],"type":{"kind":"NonNullType","type":{"kind":"NamedType","name":{"kind":"Name","value":"PageInfo"}}}}]},{"kind":"ObjectTypeDefinition","interfaces":[],"directives":[],"name":{"kind":"Name","value":"Query"},"fields":[{"kind":"FieldDefinition","name":{"kind":"Name","value":"getOptimizedQuery"},"arguments":[{"kind":"InputValueDefinition","name":{"kind":"Name","value":"queryString"},"type":{"kind":"NonNullType","type":{"kind":"NamedType","name":{"kind":"Name","value":"String"}}}}],"type":{"kind":"NamedType","name":{"kind":"Name","value":"String"}}},{"kind":"FieldDefinition","name":{"kind":"Name","value":"collection"},"arguments":[{"kind":"InputValueDefinition","name":{"kind":"Name","value":"collection"},"type":{"kind":"NamedType","name":{"kind":"Name","value":"String"}}}],"type":{"kind":"NonNullType","type":{"kind":"NamedType","name":{"kind":"Name","value":"Collection"}}}},{"kind":"FieldDefinition","name":{"kind":"Name","value":"collections"},"arguments":[],"type":{"kind":"NonNullType","type":{"kind":"ListType","type":{"kind":"NonNullType","type":{"kind":"NamedType","name":{"kind":"Name","value":"Collection"}}}}}},{"kind":"FieldDefinition","name":{"kind":"Name","value":"node"},"arguments":[{"kind":"InputValueDefinition","name":{"kind":"Name","value":"id"},"type":{"kind":"NamedType","name":{"kind":"Name","value":"String"}}}],"type":{"kind":"NonNullType","type":{"kind":"NamedType","name":{"kind":"Name","value":"Node"}}}},{"kind":"FieldDefinition","name":{"kind":"Name","value":"document"},"arguments":[{"kind":"InputValueDefinition","name":{"kind":"Name","value":"collection"},"type":{"kind":"NamedType","name":{"kind":"Name","value":"String"}}},{"kind":"InputValueDefinition","name":{"kind":"Name","value":"relativePath"},"type":{"kind":"NamedType","name":{"kind":"Name","value":"String"}}}],"type":{"kind":"NonNullType","type":{"kind":"NamedType","name":{"kind":"Name","value":"DocumentNode"}}}},{"kind":"FieldDefinition","name":{"kind":"Name","value":"pages"},"arguments":[{"kind":"InputValueDefinition","name":{"kind":"Name","value":"relativePath"},"type":{"kind":"NamedType","name":{"kind":"Name","value":"String"}}}],"type":{"kind":"NonNullType","type":{"kind":"NamedType","name":{"kind":"Name","value":"Pages"}}}},{"kind":"FieldDefinition","name":{"kind":"Name","value":"pagesConnection"},"arguments":[{"kind":"InputValueDefinition","name":{"kind":"Name","value":"before"},"type":{"kind":"NamedType","name":{"kind":"Name","value":"String"}}},{"kind":"InputValueDefinition","name":{"kind":"Name","value":"after"},"type":{"kind":"NamedType","name":{"kind":"Name","value":"String"}}},{"kind":"InputValueDefinition","name":{"kind":"Name","value":"first"},"type":{"kind":"NamedType","name":{"kind":"Name","value":"Float"}}},{"kind":"InputValueDefinition","name":{"kind":"Name","value":"last"},"type":{"kind":"NamedType","name":{"kind":"Name","value":"Float"}}},{"kind":"InputValueDefinition","name":{"kind":"Name","value":"sort"},"type":{"kind":"NamedType","name":{"kind":"Name","value":"String"}}},{"kind":"InputValueDefinition","name":{"kind":"Name","value":"filter"},"type":{"kind":"NamedType","name":{"kind":"Name","value":"PagesFilter"}}}],"type":{"kind":"NonNullType","type":{"kind":"NamedType","name":{"kind":"Name","value":"PagesConnection"}}}}]},{"kind":"InputObjectTypeDefinition","name":{"kind":"Name","value":"DocumentFilter"},"fields":[{"kind":"InputValueDefinition","name":{"kind":"Name","value":"pages"},"type":{"kind":"NamedType","name":{"kind":"Name","value":"PagesFilter"}}}]},{"kind":"ObjectTypeDefinition","interfaces":[],"directives":[],"name":{"kind":"Name","value":"DocumentConnectionEdges"},"fields":[{"kind":"FieldDefinition","name":{"kind":"Name","value":"cursor"},"arguments":[],"type":{"kind":"NonNullType","type":{"kind":"NamedType","name":{"kind":"Name","value":"String"}}}},{"kind":"FieldDefinition","name":{"kind":"Name","value":"node"},"arguments":[],"type":{"kind":"NamedType","name":{"kind":"Name","value":"DocumentNode"}}}]},{"kind":"ObjectTypeDefinition","interfaces":[{"kind":"NamedType","name":{"kind":"Name","value":"Connection"}}],"directives":[],"name":{"kind":"Name","value":"DocumentConnection"},"fields":[{"kind":"FieldDefinition","name":{"kind":"Name","value":"pageInfo"},"arguments":[],"type":{"kind":"NonNullType","type":{"kind":"NamedType","name":{"kind":"Name","value":"PageInfo"}}}},{"kind":"FieldDefinition","name":{"kind":"Name","value":"totalCount"},"arguments":[],"type":{"kind":"NonNullType","type":{"kind":"NamedType","name":{"kind":"Name","value":"Float"}}}},{"kind":"FieldDefinition","name":{"kind":"Name","value":"edges"},"arguments":[],"type":{"kind":"ListType","type":{"kind":"NamedType","name":{"kind":"Name","value":"DocumentConnectionEdges"}}}}]},{"kind":"ObjectTypeDefinition","interfaces":[],"directives":[],"name":{"kind":"Name","value":"Collection"},"fields":[{"kind":"FieldDefinition","name":{"kind":"Name","value":"name"},"arguments":[],"type":{"kind":"NonNullType","type":{"kind":"NamedType","name":{"kind":"Name","value":"String"}}}},{"kind":"FieldDefinition","name":{"kind":"Name","value":"slug"},"arguments":[],"type":{"kind":"NonNullType","type":{"kind":"NamedType","name":{"kind":"Name","value":"String"}}}},{"kind":"FieldDefinition","name":{"kind":"Name","value":"label"},"arguments":[],"type":{"kind":"NamedType","name":{"kind":"Name","value":"String"}}},{"kind":"FieldDefinition","name":{"kind":"Name","value":"path"},"arguments":[],"type":{"kind":"NonNullType","type":{"kind":"NamedType","name":{"kind":"Name","value":"String"}}}},{"kind":"FieldDefinition","name":{"kind":"Name","value":"format"},"arguments":[],"type":{"kind":"NamedType","name":{"kind":"Name","value":"String"}}},{"kind":"FieldDefinition","name":{"kind":"Name","value":"matches"},"arguments":[],"type":{"kind":"NamedType","name":{"kind":"Name","value":"String"}}},{"kind":"FieldDefinition","name":{"kind":"Name","value":"templates"},"arguments":[],"type":{"kind":"ListType","type":{"kind":"NamedType","name":{"kind":"Name","value":"JSON"}}}},{"kind":"FieldDefinition","name":{"kind":"Name","value":"fields"},"arguments":[],"type":{"kind":"ListType","type":{"kind":"NamedType","name":{"kind":"Name","value":"JSON"}}}},{"kind":"FieldDefinition","name":{"kind":"Name","value":"documents"},"arguments":[{"kind":"InputValueDefinition","name":{"kind":"Name","value":"before"},"type":{"kind":"NamedType","name":{"kind":"Name","value":"String"}}},{"kind":"InputValueDefinition","name":{"kind":"Name","value":"after"},"type":{"kind":"NamedType","name":{"kind":"Name","value":"String"}}},{"kind":"InputValueDefinition","name":{"kind":"Name","value":"first"},"type":{"kind":"NamedType","name":{"kind":"Name","value":"Float"}}},{"kind":"InputValueDefinition","name":{"kind":"Name","value":"last"},"type":{"kind":"NamedType","name":{"kind":"Name","value":"Float"}}},{"kind":"InputValueDefinition","name":{"kind":"Name","value":"sort"},"type":{"kind":"NamedType","name":{"kind":"Name","value":"String"}}},{"kind":"InputValueDefinition","name":{"kind":"Name","value":"filter"},"type":{"kind":"NamedType","name":{"kind":"Name","value":"DocumentFilter"}}},{"kind":"InputValueDefinition","name":{"kind":"Name","value":"folder"},"type":{"kind":"NamedType","name":{"kind":"Name","value":"String"}}}],"type":{"kind":"NonNullType","type":{"kind":"NamedType","name":{"kind":"Name","value":"DocumentConnection"}}}}]},{"kind":"UnionTypeDefinition","name":{"kind":"Name","value":"DocumentNode"},"directives":[],"types":[{"kind":"NamedType","name":{"kind":"Name","value":"Pages"}},{"kind":"NamedType","name":{"kind":"Name","value":"Folder"}}]},{"kind":"ObjectTypeDefinition","interfaces":[],"directives":[],"name":{"kind":"Name","value":"PagesHeroCtaPrimary"},"fields":[{"kind":"FieldDefinition","name":{"kind":"Name","value":"text"},"arguments":[],"type":{"kind":"NamedType","name":{"kind":"Name","value":"String"}}},{"kind":"FieldDefinition","name":{"kind":"Name","value":"url"},"arguments":[],"type":{"kind":"NamedType","name":{"kind":"Name","value":"String"}}}]},{"kind":"ObjectTypeDefinition","interfaces":[],"directives":[],"name":{"kind":"Name","value":"PagesHeroCtaSecondary"},"fields":[{"kind":"FieldDefinition","name":{"kind":"Name","value":"text"},"arguments":[],"type":{"kind":"NamedType","name":{"kind":"Name","value":"String"}}},{"kind":"FieldDefinition","name":{"kind":"Name","value":"url"},"arguments":[],"type":{"kind":"NamedType","name":{"kind":"Name","value":"String"}}}]},{"kind":"ObjectTypeDefinition","interfaces":[],"directives":[],"name":{"kind":"Name","value":"PagesHero"},"fields":[{"kind":"FieldDefinition","name":{"kind":"Name","value":"tagline"},"arguments":[],"type":{"kind":"NamedType","name":{"kind":"Name","value":"String"}}},{"kind":"FieldDefinition","name":{"kind":"Name","value":"heading"},"arguments":[],"type":{"kind":"NamedType","name":{"kind":"Name","value":"String"}}},{"kind":"FieldDefinition","name":{"kind":"Name","value":"description"},"arguments":[],"type":{"kind":"NamedType","name":{"kind":"Name","value":"String"}}},{"kind":"FieldDefinition","name":{"kind":"Name","value":"ctaPrimary"},"arguments":[],"type":{"kind":"NamedType","name":{"kind":"Name","value":"PagesHeroCtaPrimary"}}},{"kind":"FieldDefinition","name":{"kind":"Name","value":"ctaSecondary"},"arguments":[],"type":{"kind":"NamedType","name":{"kind":"Name","value":"PagesHeroCtaSecondary"}}}]},{"kind":"ObjectTypeDefinition","interfaces":[],"directives":[],"name":{"kind":"Name","value":"PagesServicesItems"},"fields":[{"kind":"FieldDefinition","name":{"kind":"Name","value":"title"},"arguments":[],"type":{"kind":"NonNullType","type":{"kind":"NamedType","name":{"kind":"Name","value":"String"}}}},{"kind":"FieldDefinition","name":{"kind":"Name","value":"image"},"arguments":[],"type":{"kind":"NamedType","name":{"kind":"Name","value":"String"}}},{"kind":"FieldDefinition","name":{"kind":"Name","value":"alt"},"arguments":[],"type":{"kind":"NamedType","name":{"kind":"Name","value":"String"}}},{"kind":"FieldDefinition","name":{"kind":"Name","value":"description"},"arguments":[],"type":{"kind":"NamedType","name":{"kind":"Name","value":"String"}}}]},{"kind":"ObjectTypeDefinition","interfaces":[],"directives":[],"name":{"kind":"Name","value":"PagesServices"},"fields":[{"kind":"FieldDefinition","name":{"kind":"Name","value":"heading"},"arguments":[],"type":{"kind":"NamedType","name":{"kind":"Name","value":"String"}}},{"kind":"FieldDefinition","name":{"kind":"Name","value":"items"},"arguments":[],"type":{"kind":"ListType","type":{"kind":"NamedType","name":{"kind":"Name","value":"PagesServicesItems"}}}}]},{"kind":"ObjectTypeDefinition","interfaces":[],"directives":[],"name":{"kind":"Name","value":"PagesLifts"},"fields":[{"kind":"FieldDefinition","name":{"kind":"Name","value":"badge"},"arguments":[],"type":{"kind":"NamedType","name":{"kind":"Name","value":"String"}}},{"kind":"FieldDefinition","name":{"kind":"Name","value":"heading"},"arguments":[],"type":{"kind":"NamedType","name":{"kind":"Name","value":"String"}}},{"kind":"FieldDefinition","name":{"kind":"Name","value":"description"},"arguments":[],"type":{"kind":"NamedType","name":{"kind":"Name","value":"String"}}}]},{"kind":"ObjectTypeDefinition","interfaces":[],"directives":[],"name":{"kind":"Name","value":"PagesAboutUsStats"},"fields":[{"kind":"FieldDefinition","name":{"kind":"Name","value":"value"},"arguments":[],"type":{"kind":"NonNullType","type":{"kind":"NamedType","name":{"kind":"Name","value":"Float"}}}},{"kind":"FieldDefinition","name":{"kind":"Name","value":"label"},"arguments":[],"type":{"kind":"NonNullType","type":{"kind":"NamedType","name":{"kind":"Name","value":"String"}}}}]},{"kind":"ObjectTypeDefinition","interfaces":[],"directives":[],"name":{"kind":"Name","value":"PagesAboutUsBenefits"},"fields":[{"kind":"FieldDefinition","name":{"kind":"Name","value":"text"},"arguments":[],"type":{"kind":"NonNullType","type":{"kind":"NamedType","name":{"kind":"Name","value":"String"}}}}]},{"kind":"ObjectTypeDefinition","interfaces":[],"directives":[],"name":{"kind":"Name","value":"PagesAboutUs"},"fields":[{"kind":"FieldDefinition","name":{"kind":"Name","value":"heading"},"arguments":[],"type":{"kind":"NamedType","name":{"kind":"Name","value":"String"}}},{"kind":"FieldDefinition","name":{"kind":"Name","value":"description"},"arguments":[],"type":{"kind":"NamedType","name":{"kind":"Name","value":"String"}}},{"kind":"FieldDefinition","name":{"kind":"Name","value":"descriptionSecondary"},"arguments":[],"type":{"kind":"NamedType","name":{"kind":"Name","value":"String"}}},{"kind":"FieldDefinition","name":{"kind":"Name","value":"stats"},"arguments":[],"type":{"kind":"ListType","type":{"kind":"NamedType","name":{"kind":"Name","value":"PagesAboutUsStats"}}}},{"kind":"FieldDefinition","name":{"kind":"Name","value":"benefits"},"arguments":[],"type":{"kind":"ListType","type":{"kind":"NamedType","name":{"kind":"Name","value":"PagesAboutUsBenefits"}}}}]},{"kind":"ObjectTypeDefinition","interfaces":[],"directives":[],"name":{"kind":"Name","value":"PagesSuppliersLogos"},"fields":[{"kind":"FieldDefinition","name":{"kind":"Name","value":"name"},"arguments":[],"type":{"kind":"NamedType","name":{"kind":"Name","value":"String"}}},{"kind":"FieldDefinition","name":{"kind":"Name","value":"image"},"arguments":[],"type":{"kind":"NamedType","name":{"kind":"Name","value":"String"}}},{"kind":"FieldDefinition","name":{"kind":"Name","value":"alt"},"arguments":[],"type":{"kind":"NamedType","name":{"kind":"Name","value":"String"}}}]},{"kind":"ObjectTypeDefinition","interfaces":[],"directives":[],"name":{"kind":"Name","value":"PagesSuppliers"},"fields":[{"kind":"FieldDefinition","name":{"kind":"Name","value":"heading"},"arguments":[],"type":{"kind":"NamedType","name":{"kind":"Name","value":"String"}}},{"kind":"FieldDefinition","name":{"kind":"Name","value":"description"},"arguments":[],"type":{"kind":"NamedType","name":{"kind":"Name","value":"String"}}},{"kind":"FieldDefinition","name":{"kind":"Name","value":"logos"},"arguments":[],"type":{"kind":"ListType","type":{"kind":"NamedType","name":{"kind":"Name","value":"PagesSuppliersLogos"}}}}]},{"kind":"ObjectTypeDefinition","interfaces":[],"directives":[],"name":{"kind":"Name","value":"PagesContact"},"fields":[{"kind":"FieldDefinition","name":{"kind":"Name","value":"heading"},"arguments":[],"type":{"kind":"NamedType","name":{"kind":"Name","value":"String"}}},{"kind":"FieldDefinition","name":{"kind":"Name","value":"description"},"arguments":[],"type":{"kind":"NamedType","name":{"kind":"Name","value":"String"}}},{"kind":"FieldDefinition","name":{"kind":"Name","value":"phone"},"arguments":[],"type":{"kind":"NamedType","name":{"kind":"Name","value":"String"}}},{"kind":"FieldDefinition","name":{"kind":"Name","value":"email"},"arguments":[],"type":{"kind":"NamedType","name":{"kind":"Name","value":"String"}}}]},{"kind":"ObjectTypeDefinition","interfaces":[],"directives":[],"name":{"kind":"Name","value":"PagesFaqItems"},"fields":[{"kind":"FieldDefinition","name":{"kind":"Name","value":"question"},"arguments":[],"type":{"kind":"NonNullType","type":{"kind":"NamedType","name":{"kind":"Name","value":"String"}}}},{"kind":"FieldDefinition","name":{"kind":"Name","value":"answer"},"arguments":[],"type":{"kind":"NonNullType","type":{"kind":"NamedType","name":{"kind":"Name","value":"String"}}}},{"kind":"FieldDefinition","name":{"kind":"Name","value":"icon"},"arguments":[],"type":{"kind":"NamedType","name":{"kind":"Name","value":"String"}}}]},{"kind":"ObjectTypeDefinition","interfaces":[],"directives":[],"name":{"kind":"Name","value":"PagesFaq"},"fields":[{"kind":"FieldDefinition","name":{"kind":"Name","value":"heading"},"arguments":[],"type":{"kind":"NamedType","name":{"kind":"Name","value":"String"}}},{"kind":"FieldDefinition","name":{"kind":"Name","value":"items"},"arguments":[],"type":{"kind":"ListType","type":{"kind":"NamedType","name":{"kind":"Name","value":"PagesFaqItems"}}}}]},{"kind":"ObjectTypeDefinition","interfaces":[],"directives":[],"name":{"kind":"Name","value":"PagesTableOfContents"},"fields":[{"kind":"FieldDefinition","name":{"kind":"Name","value":"label"},"arguments":[],"type":{"kind":"NamedType","name":{"kind":"Name","value":"String"}}},{"kind":"FieldDefinition","name":{"kind":"Name","value":"href"},"arguments":[],"type":{"kind":"NamedType","name":{"kind":"Name","value":"String"}}}]},{"kind":"ObjectTypeDefinition","interfaces":[],"directives":[],"name":{"kind":"Name","value":"PagesPolicySections"},"fields":[{"kind":"FieldDefinition","name":{"kind":"Name","value":"id"},"arguments":[],"type":{"kind":"NonNullType","type":{"kind":"NamedType","name":{"kind":"Name","value":"String"}}}},{"kind":"FieldDefinition","name":{"kind":"Name","value":"n"},"arguments":[],"type":{"kind":"NonNullType","type":{"kind":"NamedType","name":{"kind":"Name","value":"Float"}}}},{"kind":"FieldDefinition","name":{"kind":"Name","value":"title"},"arguments":[],"type":{"kind":"NonNullType","type":{"kind":"NamedType","name":{"kind":"Name","value":"String"}}}},{"kind":"FieldDefinition","name":{"kind":"Name","value":"content"},"arguments":[],"type":{"kind":"NonNullType","type":{"kind":"NamedType","name":{"kind":"Name","value":"JSON"}}}}]},{"kind":"ObjectTypeDefinition","interfaces":[{"kind":"NamedType","name":{"kind":"Name","value":"Node"}},{"kind":"NamedType","name":{"kind":"Name","value":"Document"}}],"directives":[],"name":{"kind":"Name","value":"Pages"},"fields":[{"kind":"FieldDefinition","name":{"kind":"Name","value":"title"},"arguments":[],"type":{"kind":"NonNullType","type":{"kind":"NamedType","name":{"kind":"Name","value":"String"}}}},{"kind":"FieldDefinition","name":{"kind":"Name","value":"hero"},"arguments":[],"type":{"kind":"NamedType","name":{"kind":"Name","value":"PagesHero"}}},{"kind":"FieldDefinition","name":{"kind":"Name","value":"services"},"arguments":[],"type":{"kind":"NamedType","name":{"kind":"Name","value":"PagesServices"}}},{"kind":"FieldDefinition","name":{"kind":"Name","value":"lifts"},"arguments":[],"type":{"kind":"NamedType","name":{"kind":"Name","value":"PagesLifts"}}},{"kind":"FieldDefinition","name":{"kind":"Name","value":"aboutUs"},"arguments":[],"type":{"kind":"NamedType","name":{"kind":"Name","value":"PagesAboutUs"}}},{"kind":"FieldDefinition","name":{"kind":"Name","value":"suppliers"},"arguments":[],"type":{"kind":"NamedType","name":{"kind":"Name","value":"PagesSuppliers"}}},{"kind":"FieldDefinition","name":{"kind":"Name","value":"contact"},"arguments":[],"type":{"kind":"NamedType","name":{"kind":"Name","value":"PagesContact"}}},{"kind":"FieldDefinition","name":{"kind":"Name","value":"faq"},"arguments":[],"type":{"kind":"NamedType","name":{"kind":"Name","value":"PagesFaq"}}},{"kind":"FieldDefinition","name":{"kind":"Name","value":"metaTitle"},"arguments":[],"type":{"kind":"NamedType","name":{"kind":"Name","value":"String"}}},{"kind":"FieldDefinition","name":{"kind":"Name","value":"metaDescription"},"arguments":[],"type":{"kind":"NamedType","name":{"kind":"Name","value":"String"}}},{"kind":"FieldDefinition","name":{"kind":"Name","value":"lastUpdate"},"arguments":[],"type":{"kind":"NamedType","name":{"kind":"Name","value":"String"}}},{"kind":"FieldDefinition","name":{"kind":"Name","value":"heading"},"arguments":[],"type":{"kind":"NamedType","name":{"kind":"Name","value":"String"}}},{"kind":"FieldDefinition","name":{"kind":"Name","value":"tableOfContents"},"arguments":[],"type":{"kind":"ListType","type":{"kind":"NamedType","name":{"kind":"Name","value":"PagesTableOfContents"}}}},{"kind":"FieldDefinition","name":{"kind":"Name","value":"policySections"},"arguments":[],"type":{"kind":"ListType","type":{"kind":"NamedType","name":{"kind":"Name","value":"PagesPolicySections"}}}},{"kind":"FieldDefinition","name":{"kind":"Name","value":"id"},"arguments":[],"type":{"kind":"NonNullType","type":{"kind":"NamedType","name":{"kind":"Name","value":"ID"}}}},{"kind":"FieldDefinition","name":{"kind":"Name","value":"_sys"},"arguments":[],"type":{"kind":"NonNullType","type":{"kind":"NamedType","name":{"kind":"Name","value":"SystemInfo"}}}},{"kind":"FieldDefinition","name":{"kind":"Name","value":"_values"},"arguments":[],"type":{"kind":"NonNullType","type":{"kind":"NamedType","name":{"kind":"Name","value":"JSON"}}}}]},{"kind":"InputObjectTypeDefinition","name":{"kind":"Name","value":"StringFilter"},"fields":[{"kind":"InputValueDefinition","name":{"kind":"Name","value":"startsWith"},"type":{"kind":"NamedType","name":{"kind":"Name","value":"String"}}},{"kind":"InputValueDefinition","name":{"kind":"Name","value":"eq"},"type":{"kind":"NamedType","name":{"kind":"Name","value":"String"}}},{"kind":"InputValueDefinition","name":{"kind":"Name","value":"exists"},"type":{"kind":"NamedType","name":{"kind":"Name","value":"Boolean"}}},{"kind":"InputValueDefinition","name":{"kind":"Name","value":"in"},"type":{"kind":"ListType","type":{"kind":"NamedType","name":{"kind":"Name","value":"String"}}}}]},{"kind":"InputObjectTypeDefinition","name":{"kind":"Name","value":"PagesHeroCtaPrimaryFilter"},"fields":[{"kind":"InputValueDefinition","name":{"kind":"Name","value":"text"},"type":{"kind":"NamedType","name":{"kind":"Name","value":"StringFilter"}}},{"kind":"InputValueDefinition","name":{"kind":"Name","value":"url"},"type":{"kind":"NamedType","name":{"kind":"Name","value":"StringFilter"}}}]},{"kind":"InputObjectTypeDefinition","name":{"kind":"Name","value":"PagesHeroCtaSecondaryFilter"},"fields":[{"kind":"InputValueDefinition","name":{"kind":"Name","value":"text"},"type":{"kind":"NamedType","name":{"kind":"Name","value":"StringFilter"}}},{"kind":"InputValueDefinition","name":{"kind":"Name","value":"url"},"type":{"kind":"NamedType","name":{"kind":"Name","value":"StringFilter"}}}]},{"kind":"InputObjectTypeDefinition","name":{"kind":"Name","value":"PagesHeroFilter"},"fields":[{"kind":"InputValueDefinition","name":{"kind":"Name","value":"tagline"},"type":{"kind":"NamedType","name":{"kind":"Name","value":"StringFilter"}}},{"kind":"InputValueDefinition","name":{"kind":"Name","value":"heading"},"type":{"kind":"NamedType","name":{"kind":"Name","value":"StringFilter"}}},{"kind":"InputValueDefinition","name":{"kind":"Name","value":"description"},"type":{"kind":"NamedType","name":{"kind":"Name","value":"StringFilter"}}},{"kind":"InputValueDefinition","name":{"kind":"Name","value":"ctaPrimary"},"type":{"kind":"NamedType","name":{"kind":"Name","value":"PagesHeroCtaPrimaryFilter"}}},{"kind":"InputValueDefinition","name":{"kind":"Name","value":"ctaSecondary"},"type":{"kind":"NamedType","name":{"kind":"Name","value":"PagesHeroCtaSecondaryFilter"}}}]},{"kind":"InputObjectTypeDefinition","name":{"kind":"Name","value":"ImageFilter"},"fields":[{"kind":"InputValueDefinition","name":{"kind":"Name","value":"startsWith"},"type":{"kind":"NamedType","name":{"kind":"Name","value":"String"}}},{"kind":"InputValueDefinition","name":{"kind":"Name","value":"eq"},"type":{"kind":"NamedType","name":{"kind":"Name","value":"String"}}},{"kind":"InputValueDefinition","name":{"kind":"Name","value":"exists"},"type":{"kind":"NamedType","name":{"kind":"Name","value":"Boolean"}}},{"kind":"InputValueDefinition","name":{"kind":"Name","value":"in"},"type":{"kind":"ListType","type":{"kind":"NamedType","name":{"kind":"Name","value":"String"}}}}]},{"kind":"InputObjectTypeDefinition","name":{"kind":"Name","value":"PagesServicesItemsFilter"},"fields":[{"kind":"InputValueDefinition","name":{"kind":"Name","value":"title"},"type":{"kind":"NamedType","name":{"kind":"Name","value":"StringFilter"}}},{"kind":"InputValueDefinition","name":{"kind":"Name","value":"image"},"type":{"kind":"NamedType","name":{"kind":"Name","value":"ImageFilter"}}},{"kind":"InputValueDefinition","name":{"kind":"Name","value":"alt"},"type":{"kind":"NamedType","name":{"kind":"Name","value":"StringFilter"}}},{"kind":"InputValueDefinition","name":{"kind":"Name","value":"description"},"type":{"kind":"NamedType","name":{"kind":"Name","value":"StringFilter"}}}]},{"kind":"InputObjectTypeDefinition","name":{"kind":"Name","value":"PagesServicesFilter"},"fields":[{"kind":"InputValueDefinition","name":{"kind":"Name","value":"heading"},"type":{"kind":"NamedType","name":{"kind":"Name","value":"StringFilter"}}},{"kind":"InputValueDefinition","name":{"kind":"Name","value":"items"},"type":{"kind":"NamedType","name":{"kind":"Name","value":"PagesServicesItemsFilter"}}}]},{"kind":"InputObjectTypeDefinition","name":{"kind":"Name","value":"PagesLiftsFilter"},"fields":[{"kind":"InputValueDefinition","name":{"kind":"Name","value":"badge"},"type":{"kind":"NamedType","name":{"kind":"Name","value":"StringFilter"}}},{"kind":"InputValueDefinition","name":{"kind":"Name","value":"heading"},"type":{"kind":"NamedType","name":{"kind":"Name","value":"StringFilter"}}},{"kind":"InputValueDefinition","name":{"kind":"Name","value":"description"},"type":{"kind":"NamedType","name":{"kind":"Name","value":"StringFilter"}}}]},{"kind":"InputObjectTypeDefinition","name":{"kind":"Name","value":"NumberFilter"},"fields":[{"kind":"InputValueDefinition","name":{"kind":"Name","value":"lt"},"type":{"kind":"NamedType","name":{"kind":"Name","value":"Float"}}},{"kind":"InputValueDefinition","name":{"kind":"Name","value":"lte"},"type":{"kind":"NamedType","name":{"kind":"Name","value":"Float"}}},{"kind":"InputValueDefinition","name":{"kind":"Name","value":"gte"},"type":{"kind":"NamedType","name":{"kind":"Name","value":"Float"}}},{"kind":"InputValueDefinition","name":{"kind":"Name","value":"gt"},"type":{"kind":"NamedType","name":{"kind":"Name","value":"Float"}}},{"kind":"InputValueDefinition","name":{"kind":"Name","value":"eq"},"type":{"kind":"NamedType","name":{"kind":"Name","value":"Float"}}},{"kind":"InputValueDefinition","name":{"kind":"Name","value":"exists"},"type":{"kind":"NamedType","name":{"kind":"Name","value":"Boolean"}}},{"kind":"InputValueDefinition","name":{"kind":"Name","value":"in"},"type":{"kind":"ListType","type":{"kind":"NamedType","name":{"kind":"Name","value":"Float"}}}}]},{"kind":"InputObjectTypeDefinition","name":{"kind":"Name","value":"PagesAboutUsStatsFilter"},"fields":[{"kind":"InputValueDefinition","name":{"kind":"Name","value":"value"},"type":{"kind":"NamedType","name":{"kind":"Name","value":"NumberFilter"}}},{"kind":"InputValueDefinition","name":{"kind":"Name","value":"label"},"type":{"kind":"NamedType","name":{"kind":"Name","value":"StringFilter"}}}]},{"kind":"InputObjectTypeDefinition","name":{"kind":"Name","value":"PagesAboutUsBenefitsFilter"},"fields":[{"kind":"InputValueDefinition","name":{"kind":"Name","value":"text"},"type":{"kind":"NamedType","name":{"kind":"Name","value":"StringFilter"}}}]},{"kind":"InputObjectTypeDefinition","name":{"kind":"Name","value":"PagesAboutUsFilter"},"fields":[{"kind":"InputValueDefinition","name":{"kind":"Name","value":"heading"},"type":{"kind":"NamedType","name":{"kind":"Name","value":"StringFilter"}}},{"kind":"InputValueDefinition","name":{"kind":"Name","value":"description"},"type":{"kind":"NamedType","name":{"kind":"Name","value":"StringFilter"}}},{"kind":"InputValueDefinition","name":{"kind":"Name","value":"descriptionSecondary"},"type":{"kind":"NamedType","name":{"kind":"Name","value":"StringFilter"}}},{"kind":"InputValueDefinition","name":{"kind":"Name","value":"stats"},"type":{"kind":"NamedType","name":{"kind":"Name","value":"PagesAboutUsStatsFilter"}}},{"kind":"InputValueDefinition","name":{"kind":"Name","value":"benefits"},"type":{"kind":"NamedType","name":{"kind":"Name","value":"PagesAboutUsBenefitsFilter"}}}]},{"kind":"InputObjectTypeDefinition","name":{"kind":"Name","value":"PagesSuppliersLogosFilter"},"fields":[{"kind":"InputValueDefinition","name":{"kind":"Name","value":"name"},"type":{"kind":"NamedType","name":{"kind":"Name","value":"StringFilter"}}},{"kind":"InputValueDefinition","name":{"kind":"Name","value":"image"},"type":{"kind":"NamedType","name":{"kind":"Name","value":"ImageFilter"}}},{"kind":"InputValueDefinition","name":{"kind":"Name","value":"alt"},"type":{"kind":"NamedType","name":{"kind":"Name","value":"StringFilter"}}}]},{"kind":"InputObjectTypeDefinition","name":{"kind":"Name","value":"PagesSuppliersFilter"},"fields":[{"kind":"InputValueDefinition","name":{"kind":"Name","value":"heading"},"type":{"kind":"NamedType","name":{"kind":"Name","value":"StringFilter"}}},{"kind":"InputValueDefinition","name":{"kind":"Name","value":"description"},"type":{"kind":"NamedType","name":{"kind":"Name","value":"StringFilter"}}},{"kind":"InputValueDefinition","name":{"kind":"Name","value":"logos"},"type":{"kind":"NamedType","name":{"kind":"Name","value":"PagesSuppliersLogosFilter"}}}]},{"kind":"InputObjectTypeDefinition","name":{"kind":"Name","value":"PagesContactFilter"},"fields":[{"kind":"InputValueDefinition","name":{"kind":"Name","value":"heading"},"type":{"kind":"NamedType","name":{"kind":"Name","value":"StringFilter"}}},{"kind":"InputValueDefinition","name":{"kind":"Name","value":"description"},"type":{"kind":"NamedType","name":{"kind":"Name","value":"StringFilter"}}},{"kind":"InputValueDefinition","name":{"kind":"Name","value":"phone"},"type":{"kind":"NamedType","name":{"kind":"Name","value":"StringFilter"}}},{"kind":"InputValueDefinition","name":{"kind":"Name","value":"email"},"type":{"kind":"NamedType","name":{"kind":"Name","value":"StringFilter"}}}]},{"kind":"InputObjectTypeDefinition","name":{"kind":"Name","value":"PagesFaqItemsFilter"},"fields":[{"kind":"InputValueDefinition","name":{"kind":"Name","value":"question"},"type":{"kind":"NamedType","name":{"kind":"Name","value":"StringFilter"}}},{"kind":"InputValueDefinition","name":{"kind":"Name","value":"answer"},"type":{"kind":"NamedType","name":{"kind":"Name","value":"StringFilter"}}},{"kind":"InputValueDefinition","name":{"kind":"Name","value":"icon"},"type":{"kind":"NamedType","name":{"kind":"Name","value":"StringFilter"}}}]},{"kind":"InputObjectTypeDefinition","name":{"kind":"Name","value":"PagesFaqFilter"},"fields":[{"kind":"InputValueDefinition","name":{"kind":"Name","value":"heading"},"type":{"kind":"NamedType","name":{"kind":"Name","value":"StringFilter"}}},{"kind":"InputValueDefinition","name":{"kind":"Name","value":"items"},"type":{"kind":"NamedType","name":{"kind":"Name","value":"PagesFaqItemsFilter"}}}]},{"kind":"InputObjectTypeDefinition","name":{"kind":"Name","value":"PagesTableOfContentsFilter"},"fields":[{"kind":"InputValueDefinition","name":{"kind":"Name","value":"label"},"type":{"kind":"NamedType","name":{"kind":"Name","value":"StringFilter"}}},{"kind":"InputValueDefinition","name":{"kind":"Name","value":"href"},"type":{"kind":"NamedType","name":{"kind":"Name","value":"StringFilter"}}}]},{"kind":"InputObjectTypeDefinition","name":{"kind":"Name","value":"RichTextFilter"},"fields":[{"kind":"InputValueDefinition","name":{"kind":"Name","value":"startsWith"},"type":{"kind":"NamedType","name":{"kind":"Name","value":"String"}}},{"kind":"InputValueDefinition","name":{"kind":"Name","value":"eq"},"type":{"kind":"NamedType","name":{"kind":"Name","value":"String"}}},{"kind":"InputValueDefinition","name":{"kind":"Name","value":"exists"},"type":{"kind":"NamedType","name":{"kind":"Name","value":"Boolean"}}}]},{"kind":"InputObjectTypeDefinition","name":{"kind":"Name","value":"PagesPolicySectionsFilter"},"fields":[{"kind":"InputValueDefinition","name":{"kind":"Name","value":"id"},"type":{"kind":"NamedType","name":{"kind":"Name","value":"StringFilter"}}},{"kind":"InputValueDefinition","name":{"kind":"Name","value":"n"},"type":{"kind":"NamedType","name":{"kind":"Name","value":"NumberFilter"}}},{"kind":"InputValueDefinition","name":{"kind":"Name","value":"title"},"type":{"kind":"NamedType","name":{"kind":"Name","value":"StringFilter"}}},{"kind":"InputValueDefinition","name":{"kind":"Name","value":"content"},"type":{"kind":"NamedType","name":{"kind":"Name","value":"RichTextFilter"}}}]},{"kind":"InputObjectTypeDefinition","name":{"kind":"Name","value":"PagesFilter"},"fields":[{"kind":"InputValueDefinition","name":{"kind":"Name","value":"title"},"type":{"kind":"NamedType","name":{"kind":"Name","value":"StringFilter"}}},{"kind":"InputValueDefinition","name":{"kind":"Name","value":"hero"},"type":{"kind":"NamedType","name":{"kind":"Name","value":"PagesHeroFilter"}}},{"kind":"InputValueDefinition","name":{"kind":"Name","value":"services"},"type":{"kind":"NamedType","name":{"kind":"Name","value":"PagesServicesFilter"}}},{"kind":"InputValueDefinition","name":{"kind":"Name","value":"lifts"},"type":{"kind":"NamedType","name":{"kind":"Name","value":"PagesLiftsFilter"}}},{"kind":"InputValueDefinition","name":{"kind":"Name","value":"aboutUs"},"type":{"kind":"NamedType","name":{"kind":"Name","value":"PagesAboutUsFilter"}}},{"kind":"InputValueDefinition","name":{"kind":"Name","value":"suppliers"},"type":{"kind":"NamedType","name":{"kind":"Name","value":"PagesSuppliersFilter"}}},{"kind":"InputValueDefinition","name":{"kind":"Name","value":"contact"},"type":{"kind":"NamedType","name":{"kind":"Name","value":"PagesContactFilter"}}},{"kind":"InputValueDefinition","name":{"kind":"Name","value":"faq"},"type":{"kind":"NamedType","name":{"kind":"Name","value":"PagesFaqFilter"}}},{"kind":"InputValueDefinition","name":{"kind":"Name","value":"metaTitle"},"type":{"kind":"NamedType","name":{"kind":"Name","value":"StringFilter"}}},{"kind":"InputValueDefinition","name":{"kind":"Name","value":"metaDescription"},"type":{"kind":"NamedType","name":{"kind":"Name","value":"StringFilter"}}},{"kind":"InputValueDefinition","name":{"kind":"Name","value":"lastUpdate"},"type":{"kind":"NamedType","name":{"kind":"Name","value":"StringFilter"}}},{"kind":"InputValueDefinition","name":{"kind":"Name","value":"heading"},"type":{"kind":"NamedType","name":{"kind":"Name","value":"StringFilter"}}},{"kind":"InputValueDefinition","name":{"kind":"Name","value":"tableOfContents"},"type":{"kind":"NamedType","name":{"kind":"Name","value":"PagesTableOfContentsFilter"}}},{"kind":"InputValueDefinition","name":{"kind":"Name","value":"policySections"},"type":{"kind":"NamedType","name":{"kind":"Name","value":"PagesPolicySectionsFilter"}}}]},{"kind":"ObjectTypeDefinition","interfaces":[],"directives":[],"name":{"kind":"Name","value":"PagesConnectionEdges"},"fields":[{"kind":"FieldDefinition","name":{"kind":"Name","value":"cursor"},"arguments":[],"type":{"kind":"NonNullType","type":{"kind":"NamedType","name":{"kind":"Name","value":"String"}}}},{"kind":"FieldDefinition","name":{"kind":"Name","value":"node"},"arguments":[],"type":{"kind":"NamedType","name":{"kind":"Name","value":"Pages"}}}]},{"kind":"ObjectTypeDefinition","interfaces":[{"kind":"NamedType","name":{"kind":"Name","value":"Connection"}}],"directives":[],"name":{"kind":"Name","value":"PagesConnection"},"fields":[{"kind":"FieldDefinition","name":{"kind":"Name","value":"pageInfo"},"arguments":[],"type":{"kind":"NonNullType","type":{"kind":"NamedType","name":{"kind":"Name","value":"PageInfo"}}}},{"kind":"FieldDefinition","name":{"kind":"Name","value":"totalCount"},"arguments":[],"type":{"kind":"NonNullType","type":{"kind":"NamedType","name":{"kind":"Name","value":"Float"}}}},{"kind":"FieldDefinition","name":{"kind":"Name","value":"edges"},"arguments":[],"type":{"kind":"ListType","type":{"kind":"NamedType","name":{"kind":"Name","value":"PagesConnectionEdges"}}}}]},{"kind":"ObjectTypeDefinition","interfaces":[],"directives":[],"name":{"kind":"Name","value":"Mutation"},"fields":[{"kind":"FieldDefinition","name":{"kind":"Name","value":"addPendingDocument"},"arguments":[{"kind":"InputValueDefinition","name":{"kind":"Name","value":"collection"},"type":{"kind":"NonNullType","type":{"kind":"NamedType","name":{"kind":"Name","value":"String"}}}},{"kind":"InputValueDefinition","name":{"kind":"Name","value":"relativePath"},"type":{"kind":"NonNullType","type":{"kind":"NamedType","name":{"kind":"Name","value":"String"}}}},{"kind":"InputValueDefinition","name":{"kind":"Name","value":"template"},"type":{"kind":"NamedType","name":{"kind":"Name","value":"String"}}}],"type":{"kind":"NonNullType","type":{"kind":"NamedType","name":{"kind":"Name","value":"DocumentNode"}}}},{"kind":"FieldDefinition","name":{"kind":"Name","value":"updateDocument"},"arguments":[{"kind":"InputValueDefinition","name":{"kind":"Name","value":"collection"},"type":{"kind":"NamedType","name":{"kind":"Name","value":"String"}}},{"kind":"InputValueDefinition","name":{"kind":"Name","value":"relativePath"},"type":{"kind":"NonNullType","type":{"kind":"NamedType","name":{"kind":"Name","value":"String"}}}},{"kind":"InputValueDefinition","name":{"kind":"Name","value":"params"},"type":{"kind":"NonNullType","type":{"kind":"NamedType","name":{"kind":"Name","value":"DocumentUpdateMutation"}}}}],"type":{"kind":"NonNullType","type":{"kind":"NamedType","name":{"kind":"Name","value":"DocumentNode"}}}},{"kind":"FieldDefinition","name":{"kind":"Name","value":"deleteDocument"},"arguments":[{"kind":"InputValueDefinition","name":{"kind":"Name","value":"collection"},"type":{"kind":"NamedType","name":{"kind":"Name","value":"String"}}},{"kind":"InputValueDefinition","name":{"kind":"Name","value":"relativePath"},"type":{"kind":"NonNullType","type":{"kind":"NamedType","name":{"kind":"Name","value":"String"}}}}],"type":{"kind":"NonNullType","type":{"kind":"NamedType","name":{"kind":"Name","value":"DocumentNode"}}}},{"kind":"FieldDefinition","name":{"kind":"Name","value":"createDocument"},"arguments":[{"kind":"InputValueDefinition","name":{"kind":"Name","value":"collection"},"type":{"kind":"NamedType","name":{"kind":"Name","value":"String"}}},{"kind":"InputValueDefinition","name":{"kind":"Name","value":"relativePath"},"type":{"kind":"NonNullType","type":{"kind":"NamedType","name":{"kind":"Name","value":"String"}}}},{"kind":"InputValueDefinition","name":{"kind":"Name","value":"params"},"type":{"kind":"NonNullType","type":{"kind":"NamedType","name":{"kind":"Name","value":"DocumentMutation"}}}}],"type":{"kind":"NonNullType","type":{"kind":"NamedType","name":{"kind":"Name","value":"DocumentNode"}}}},{"kind":"FieldDefinition","name":{"kind":"Name","value":"createFolder"},"arguments":[{"kind":"InputValueDefinition","name":{"kind":"Name","value":"collection"},"type":{"kind":"NamedType","name":{"kind":"Name","value":"String"}}},{"kind":"InputValueDefinition","name":{"kind":"Name","value":"relativePath"},"type":{"kind":"NonNullType","type":{"kind":"NamedType","name":{"kind":"Name","value":"String"}}}}],"type":{"kind":"NonNullType","type":{"kind":"NamedType","name":{"kind":"Name","value":"DocumentNode"}}}},{"kind":"FieldDefinition","name":{"kind":"Name","value":"updatePages"},"arguments":[{"kind":"InputValueDefinition","name":{"kind":"Name","value":"relativePath"},"type":{"kind":"NonNullType","type":{"kind":"NamedType","name":{"kind":"Name","value":"String"}}}},{"kind":"InputValueDefinition","name":{"kind":"Name","value":"params"},"type":{"kind":"NonNullType","type":{"kind":"NamedType","name":{"kind":"Name","value":"PagesMutation"}}}}],"type":{"kind":"NonNullType","type":{"kind":"NamedType","name":{"kind":"Name","value":"Pages"}}}},{"kind":"FieldDefinition","name":{"kind":"Name","value":"createPages"},"arguments":[{"kind":"InputValueDefinition","name":{"kind":"Name","value":"relativePath"},"type":{"kind":"NonNullType","type":{"kind":"NamedType","name":{"kind":"Name","value":"String"}}}},{"kind":"InputValueDefinition","name":{"kind":"Name","value":"params"},"type":{"kind":"NonNullType","type":{"kind":"NamedType","name":{"kind":"Name","value":"PagesMutation"}}}}],"type":{"kind":"NonNullType","type":{"kind":"NamedType","name":{"kind":"Name","value":"Pages"}}}}]},{"kind":"InputObjectTypeDefinition","name":{"kind":"Name","value":"DocumentUpdateMutation"},"fields":[{"kind":"InputValueDefinition","name":{"kind":"Name","value":"pages"},"type":{"kind":"NamedType","name":{"kind":"Name","value":"PagesMutation"}}},{"kind":"InputValueDefinition","name":{"kind":"Name","value":"relativePath"},"type":{"kind":"NamedType","name":{"kind":"Name","value":"String"}}}]},{"kind":"InputObjectTypeDefinition","name":{"kind":"Name","value":"DocumentMutation"},"fields":[{"kind":"InputValueDefinition","name":{"kind":"Name","value":"pages"},"type":{"kind":"NamedType","name":{"kind":"Name","value":"PagesMutation"}}}]},{"kind":"InputObjectTypeDefinition","name":{"kind":"Name","value":"PagesHeroCtaPrimaryMutation"},"fields":[{"kind":"InputValueDefinition","name":{"kind":"Name","value":"text"},"type":{"kind":"NamedType","name":{"kind":"Name","value":"String"}}},{"kind":"InputValueDefinition","name":{"kind":"Name","value":"url"},"type":{"kind":"NamedType","name":{"kind":"Name","value":"String"}}}]},{"kind":"InputObjectTypeDefinition","name":{"kind":"Name","value":"PagesHeroCtaSecondaryMutation"},"fields":[{"kind":"InputValueDefinition","name":{"kind":"Name","value":"text"},"type":{"kind":"NamedType","name":{"kind":"Name","value":"String"}}},{"kind":"InputValueDefinition","name":{"kind":"Name","value":"url"},"type":{"kind":"NamedType","name":{"kind":"Name","value":"String"}}}]},{"kind":"InputObjectTypeDefinition","name":{"kind":"Name","value":"PagesHeroMutation"},"fields":[{"kind":"InputValueDefinition","name":{"kind":"Name","value":"tagline"},"type":{"kind":"NamedType","name":{"kind":"Name","value":"String"}}},{"kind":"InputValueDefinition","name":{"kind":"Name","value":"heading"},"type":{"kind":"NamedType","name":{"kind":"Name","value":"String"}}},{"kind":"InputValueDefinition","name":{"kind":"Name","value":"description"},"type":{"kind":"NamedType","name":{"kind":"Name","value":"String"}}},{"kind":"InputValueDefinition","name":{"kind":"Name","value":"ctaPrimary"},"type":{"kind":"NamedType","name":{"kind":"Name","value":"PagesHeroCtaPrimaryMutation"}}},{"kind":"InputValueDefinition","name":{"kind":"Name","value":"ctaSecondary"},"type":{"kind":"NamedType","name":{"kind":"Name","value":"PagesHeroCtaSecondaryMutation"}}}]},{"kind":"InputObjectTypeDefinition","name":{"kind":"Name","value":"PagesServicesItemsMutation"},"fields":[{"kind":"InputValueDefinition","name":{"kind":"Name","value":"title"},"type":{"kind":"NamedType","name":{"kind":"Name","value":"String"}}},{"kind":"InputValueDefinition","name":{"kind":"Name","value":"image"},"type":{"kind":"NamedType","name":{"kind":"Name","value":"String"}}},{"kind":"InputValueDefinition","name":{"kind":"Name","value":"alt"},"type":{"kind":"NamedType","name":{"kind":"Name","value":"String"}}},{"kind":"InputValueDefinition","name":{"kind":"Name","value":"description"},"type":{"kind":"NamedType","name":{"kind":"Name","value":"String"}}}]},{"kind":"InputObjectTypeDefinition","name":{"kind":"Name","value":"PagesServicesMutation"},"fields":[{"kind":"InputValueDefinition","name":{"kind":"Name","value":"heading"},"type":{"kind":"NamedType","name":{"kind":"Name","value":"String"}}},{"kind":"InputValueDefinition","name":{"kind":"Name","value":"items"},"type":{"kind":"ListType","type":{"kind":"NamedType","name":{"kind":"Name","value":"PagesServicesItemsMutation"}}}}]},{"kind":"InputObjectTypeDefinition","name":{"kind":"Name","value":"PagesLiftsMutation"},"fields":[{"kind":"InputValueDefinition","name":{"kind":"Name","value":"badge"},"type":{"kind":"NamedType","name":{"kind":"Name","value":"String"}}},{"kind":"InputValueDefinition","name":{"kind":"Name","value":"heading"},"type":{"kind":"NamedType","name":{"kind":"Name","value":"String"}}},{"kind":"InputValueDefinition","name":{"kind":"Name","value":"description"},"type":{"kind":"NamedType","name":{"kind":"Name","value":"String"}}}]},{"kind":"InputObjectTypeDefinition","name":{"kind":"Name","value":"PagesAboutUsStatsMutation"},"fields":[{"kind":"InputValueDefinition","name":{"kind":"Name","value":"value"},"type":{"kind":"NamedType","name":{"kind":"Name","value":"Float"}}},{"kind":"InputValueDefinition","name":{"kind":"Name","value":"label"},"type":{"kind":"NamedType","name":{"kind":"Name","value":"String"}}}]},{"kind":"InputObjectTypeDefinition","name":{"kind":"Name","value":"PagesAboutUsBenefitsMutation"},"fields":[{"kind":"InputValueDefinition","name":{"kind":"Name","value":"text"},"type":{"kind":"NamedType","name":{"kind":"Name","value":"String"}}}]},{"kind":"InputObjectTypeDefinition","name":{"kind":"Name","value":"PagesAboutUsMutation"},"fields":[{"kind":"InputValueDefinition","name":{"kind":"Name","value":"heading"},"type":{"kind":"NamedType","name":{"kind":"Name","value":"String"}}},{"kind":"InputValueDefinition","name":{"kind":"Name","value":"description"},"type":{"kind":"NamedType","name":{"kind":"Name","value":"String"}}},{"kind":"InputValueDefinition","name":{"kind":"Name","value":"descriptionSecondary"},"type":{"kind":"NamedType","name":{"kind":"Name","value":"String"}}},{"kind":"InputValueDefinition","name":{"kind":"Name","value":"stats"},"type":{"kind":"ListType","type":{"kind":"NamedType","name":{"kind":"Name","value":"PagesAboutUsStatsMutation"}}}},{"kind":"InputValueDefinition","name":{"kind":"Name","value":"benefits"},"type":{"kind":"ListType","type":{"kind":"NamedType","name":{"kind":"Name","value":"PagesAboutUsBenefitsMutation"}}}}]},{"kind":"InputObjectTypeDefinition","name":{"kind":"Name","value":"PagesSuppliersLogosMutation"},"fields":[{"kind":"InputValueDefinition","name":{"kind":"Name","value":"name"},"type":{"kind":"NamedType","name":{"kind":"Name","value":"String"}}},{"kind":"InputValueDefinition","name":{"kind":"Name","value":"image"},"type":{"kind":"NamedType","name":{"kind":"Name","value":"String"}}},{"kind":"InputValueDefinition","name":{"kind":"Name","value":"alt"},"type":{"kind":"NamedType","name":{"kind":"Name","value":"String"}}}]},{"kind":"InputObjectTypeDefinition","name":{"kind":"Name","value":"PagesSuppliersMutation"},"fields":[{"kind":"InputValueDefinition","name":{"kind":"Name","value":"heading"},"type":{"kind":"NamedType","name":{"kind":"Name","value":"String"}}},{"kind":"InputValueDefinition","name":{"kind":"Name","value":"description"},"type":{"kind":"NamedType","name":{"kind":"Name","value":"String"}}},{"kind":"InputValueDefinition","name":{"kind":"Name","value":"logos"},"type":{"kind":"ListType","type":{"kind":"NamedType","name":{"kind":"Name","value":"PagesSuppliersLogosMutation"}}}}]},{"kind":"InputObjectTypeDefinition","name":{"kind":"Name","value":"PagesContactMutation"},"fields":[{"kind":"InputValueDefinition","name":{"kind":"Name","value":"heading"},"type":{"kind":"NamedType","name":{"kind":"Name","value":"String"}}},{"kind":"InputValueDefinition","name":{"kind":"Name","value":"description"},"type":{"kind":"NamedType","name":{"kind":"Name","value":"String"}}},{"kind":"InputValueDefinition","name":{"kind":"Name","value":"phone"},"type":{"kind":"NamedType","name":{"kind":"Name","value":"String"}}},{"kind":"InputValueDefinition","name":{"kind":"Name","value":"email"},"type":{"kind":"NamedType","name":{"kind":"Name","value":"String"}}}]},{"kind":"InputObjectTypeDefinition","name":{"kind":"Name","value":"PagesFaqItemsMutation"},"fields":[{"kind":"InputValueDefinition","name":{"kind":"Name","value":"question"},"type":{"kind":"NamedType","name":{"kind":"Name","value":"String"}}},{"kind":"InputValueDefinition","name":{"kind":"Name","value":"answer"},"type":{"kind":"NamedType","name":{"kind":"Name","value":"String"}}},{"kind":"InputValueDefinition","name":{"kind":"Name","value":"icon"},"type":{"kind":"NamedType","name":{"kind":"Name","value":"String"}}}]},{"kind":"InputObjectTypeDefinition","name":{"kind":"Name","value":"PagesFaqMutation"},"fields":[{"kind":"InputValueDefinition","name":{"kind":"Name","value":"heading"},"type":{"kind":"NamedType","name":{"kind":"Name","value":"String"}}},{"kind":"InputValueDefinition","name":{"kind":"Name","value":"items"},"type":{"kind":"ListType","type":{"kind":"NamedType","name":{"kind":"Name","value":"PagesFaqItemsMutation"}}}}]},{"kind":"InputObjectTypeDefinition","name":{"kind":"Name","value":"PagesTableOfContentsMutation"},"fields":[{"kind":"InputValueDefinition","name":{"kind":"Name","value":"label"},"type":{"kind":"NamedType","name":{"kind":"Name","value":"String"}}},{"kind":"InputValueDefinition","name":{"kind":"Name","value":"href"},"type":{"kind":"NamedType","name":{"kind":"Name","value":"String"}}}]},{"kind":"InputObjectTypeDefinition","name":{"kind":"Name","value":"PagesPolicySectionsMutation"},"fields":[{"kind":"InputValueDefinition","name":{"kind":"Name","value":"id"},"type":{"kind":"NamedType","name":{"kind":"Name","value":"String"}}},{"kind":"InputValueDefinition","name":{"kind":"Name","value":"n"},"type":{"kind":"NamedType","name":{"kind":"Name","value":"Float"}}},{"kind":"InputValueDefinition","name":{"kind":"Name","value":"title"},"type":{"kind":"NamedType","name":{"kind":"Name","value":"String"}}},{"kind":"InputValueDefinition","name":{"kind":"Name","value":"content"},"type":{"kind":"NamedType","name":{"kind":"Name","value":"JSON"}}}]},{"kind":"InputObjectTypeDefinition","name":{"kind":"Name","value":"PagesMutation"},"fields":[{"kind":"InputValueDefinition","name":{"kind":"Name","value":"title"},"type":{"kind":"NamedType","name":{"kind":"Name","value":"String"}}},{"kind":"InputValueDefinition","name":{"kind":"Name","value":"hero"},"type":{"kind":"NamedType","name":{"kind":"Name","value":"PagesHeroMutation"}}},{"kind":"InputValueDefinition","name":{"kind":"Name","value":"services"},"type":{"kind":"NamedType","name":{"kind":"Name","value":"PagesServicesMutation"}}},{"kind":"InputValueDefinition","name":{"kind":"Name","value":"lifts"},"type":{"kind":"NamedType","name":{"kind":"Name","value":"PagesLiftsMutation"}}},{"kind":"InputValueDefinition","name":{"kind":"Name","value":"aboutUs"},"type":{"kind":"NamedType","name":{"kind":"Name","value":"PagesAboutUsMutation"}}},{"kind":"InputValueDefinition","name":{"kind":"Name","value":"suppliers"},"type":{"kind":"NamedType","name":{"kind":"Name","value":"PagesSuppliersMutation"}}},{"kind":"InputValueDefinition","name":{"kind":"Name","value":"contact"},"type":{"kind":"NamedType","name":{"kind":"Name","value":"PagesContactMutation"}}},{"kind":"InputValueDefinition","name":{"kind":"Name","value":"faq"},"type":{"kind":"NamedType","name":{"kind":"Name","value":"PagesFaqMutation"}}},{"kind":"InputValueDefinition","name":{"kind":"Name","value":"metaTitle"},"type":{"kind":"NamedType","name":{"kind":"Name","value":"String"}}},{"kind":"InputValueDefinition","name":{"kind":"Name","value":"metaDescription"},"type":{"kind":"NamedType","name":{"kind":"Name","value":"String"}}},{"kind":"InputValueDefinition","name":{"kind":"Name","value":"lastUpdate"},"type":{"kind":"NamedType","name":{"kind":"Name","value":"String"}}},{"kind":"InputValueDefinition","name":{"kind":"Name","value":"heading"},"type":{"kind":"NamedType","name":{"kind":"Name","value":"String"}}},{"kind":"InputValueDefinition","name":{"kind":"Name","value":"tableOfContents"},"type":{"kind":"ListType","type":{"kind":"NamedType","name":{"kind":"Name","value":"PagesTableOfContentsMutation"}}}},{"kind":"InputValueDefinition","name":{"kind":"Name","value":"policySections"},"type":{"kind":"ListType","type":{"kind":"NamedType","name":{"kind":"Name","value":"PagesPolicySectionsMutation"}}}}]}]}}